WarzoneTracker/__init__.py
WarzoneTracker/api.py
WarzoneTracker/controller.py
WarzoneTracker/parser.py
WarzoneTracker-0.0.1.dist-info/LICENSE
WarzoneTracker-0.0.1.dist-info/METADATA
WarzoneTracker-0.0.1.dist-info/WHEEL
WarzoneTracker-0.0.1.dist-info/top_level.txt
WarzoneTracker-0.0.1.dist-info/RECORD
